cogchain/__init__.py
cogchain/errors.py
cogchain/interfaces/__init__.py
cogchain/models/__init__.py
cogchain-0.1.0.dist-info/METADATA
cogchain-0.1.0.dist-info/WHEEL
cogchain-0.1.0.dist-info/RECORD
