Metadata-Version: 2.4
Name: cogchain
Version: 0.1.0
Summary: Shared interfaces and models for d-cogs
Project-URL: Homepage, https://github.com/nntin/d-cogs
Project-URL: Source, https://github.com/nntin/d-cogs/tree/main/cogchain
Author: d-cogs maintainers
License: MIT
Requires-Python: >=3.9
Requires-Dist: discord-py>=2.3.0
Requires-Dist: langchain-core>=0.3.0
Requires-Dist: orjson>=3.9.10
Requires-Dist: pydantic>=1.10.0
Requires-Dist: red-discordbot>=3.5.0
